odoo/addons/base_sequence_option/README.rst
odoo/addons/base_sequence_option/__init__.py
odoo/addons/base_sequence_option/__manifest__.py
odoo/addons/base_sequence_option/i18n/base_sequence_option.pot
odoo/addons/base_sequence_option/i18n/it.po
odoo/addons/base_sequence_option/models/__init__.py
odoo/addons/base_sequence_option/models/ir_sequence.py
odoo/addons/base_sequence_option/models/ir_sequence_option.py
odoo/addons/base_sequence_option/readme/CONTRIBUTORS.rst
odoo/addons/base_sequence_option/readme/DESCRIPTION.rst
odoo/addons/base_sequence_option/readme/USAGE.rst
odoo/addons/base_sequence_option/security/ir.model.access.csv
odoo/addons/base_sequence_option/security/sequence_option_security.xml
odoo/addons/base_sequence_option/static/description/icon.png
odoo/addons/base_sequence_option/static/description/index.html
odoo/addons/base_sequence_option/tests/__init__.py
odoo/addons/base_sequence_option/tests/base_sequence_tester.py
odoo/addons/base_sequence_option/tests/common.py
odoo/addons/base_sequence_option/tests/test_ir_sequence_option.py
odoo/addons/base_sequence_option/views/sequence_option_view.xml
odoo14_addon_base_sequence_option-14.0.1.0.1.dist-info/METADATA
odoo14_addon_base_sequence_option-14.0.1.0.1.dist-info/WHEEL
odoo14_addon_base_sequence_option-14.0.1.0.1.dist-info/top_level.txt
odoo14_addon_base_sequence_option-14.0.1.0.1.dist-info/RECORD
